linzt_scrna_test/__init__.py
linzt_scrna_test/__main__.py
linzt_scrna_test/server.py
linzt_scrna_test-0.3.0.dist-info/WHEEL
linzt_scrna_test-0.3.0.dist-info/entry_points.txt
linzt_scrna_test-0.3.0.dist-info/METADATA
linzt_scrna_test-0.3.0.dist-info/RECORD
