Metadata-Version: 2.3
Name: linzt-scrna-test
Version: 0.3.0
Summary: MCP server providing tools for scRNA analysis
Keywords: mcp,llm
Author: linzt
License: MIT
Classifier: Development Status :: 4 - Beta
Classifier: Intended Audience :: Developers
Classifier: License :: OSI Approved :: MIT License
Classifier: Programming Language :: Python :: 3
Classifier: Programming Language :: Python :: 3.10
Requires-Dist: mcp>=1.22.0
Requires-Dist: pydantic>=2.12.5
Maintainer: linzt
Maintainer-email: linzt <linzeteng123@163.com>
Requires-Python: >=3.10
